{
    "subscriptions": {
      "personal": {
        "0": {
          "name": "Amigo Joven",
          "cost": "15 €/año (12 € desgravables)",
          "requirements": "Hasta 18 años.",
          "benefits": [
            { "icon": "", "name": "Carnet personalizado" },
            { "icon": "", "name": "Acceso a eventos educativos sobre la Alhambra" },
            { "icon": "", "name": "Descuentos en talleres especializados" }
          ]
        },
        "1": {
          "name": "Amigo Estudiante",
          "cost": "25 €/año (20 € desgravables)",
          "requirements": "Hasta 25 años o egresados universitarios antes de los 25 años. Estudiantes de cualquier universidad española o Erasmus de la UGR.",
          "benefits": [
            { "icon": "", "name": "Carnet personalizado" },
            { "icon": "", "name": "Eventos de networking y voluntariado" },
            { "icon": "", "name": "Descuentos en actividades culturales" },
            { "icon": "", "name": "Colaboración en la comunidad virtual de Amigos de la Alhambra" }
          ]
        },
        "2": {
          "name": "Guardián de la Alhambra",
          "cost": "100 €/año (80 € desgravables)",
          "requirements": "A partir de 25 años.",
          "benefits": [
            { "icon": "", "name": "Carnet personalizado" },
            { "icon": "", "name": "Welcome Pack (paquete de bienvenida)" },
            { "icon": "", "name": "Descuentos en entradas a actividades, conferencias y publicaciones" },
            { "icon": "", "name": "Invitación a la recepción anual con acceso al 'Libro de firmas'" }
          ]
        },
        "3": {
          "name": "Familia Amiga",
          "cost": "200 €/año (160 € desgravables)",
          "requirements": "A partir de 25 años. Incluye a dos adultos y tres menores de 18 años de la unidad familiar.",
          "benefits": [
            { "icon": "", "name": "Carnet personalizado" },
            { "icon": "", "name": "Welcome Pack" },
            { "icon": "", "name": "Descuentos en entradas, publicaciones, talleres y actividades infantiles" },
            { "icon": "", "name": "Invitación a la recepción anual con acceso al 'Libro de firmas'" },
            { "icon": "", "name": "Acceso exclusivo a eventos educativos, networking, voluntariado y guías expertos" }
          ]
        },
        "4": {
          "name": "Círculo 1238",
          "cost": "Primer año: 1.000 €, A partir del segundo año: 150 €/año (120 € desgravables)",
          "requirements": "A partir de 25 años.",
          "benefits": [
            { "icon": "", "name": "Carnet personalizado" },
            { "icon": "", "name": "Welcome Pack" },
            { "icon": "", "name": "Descuentos en actividades, publicaciones y cursos infantiles" },
            { "icon": "", "name": "Invitación a la recepción anual con acceso al 'Libro de firmas'" },
            { "icon": "", "name": "Visita privada anual en grupo al conjunto monumental de la Alhambra" },
            { "icon": "", "name": "Participación en encuestas para diseñar exposiciones y eventos" },
            { "icon": "", "name": "Desayuno con la dirección de la Alhambra" },
            { "icon": "", "name": "Preferencia en la compra de entradas VIP para conciertos seleccionados" }
          ]
        }
      },
      "empresa": {
        "0": {
          "name": "Empresas e Instituciones",
          "cost": "Personalizado",
          "requirements": "Ser una empresa o institución interesada en colaborar con la Fundación Amigos de la Alhambra.",
          "benefits": [
            { "icon": "", "name": "Co-branding: Eventos corporativos exclusivos y visibilidad en actividades" },
            { "icon": "", "name": "Publicaciones especiales: Materiales relacionados con la Alhambra y Granada" },
            { "icon": "", "name": "Reconocimiento público: Mención en la web y memoria anual" },
            { "icon": "", "name": "Agradecimiento en actos públicos realizados por la Fundación" },
            { "icon": "", "name": "Logotipo en la página web de la Fundación" },
            { "icon": "", "name": "Condiciones ventajosas para empleados interesados en ser Amigos de la Fundación" },
            { "icon": "", "name": "Atención personalizada: Organización de visitas institucionales adaptadas" }
          ]
        }
      }
    }
  }
  